epitech_console/__init__.py
epitech_console/config.ini
epitech_console/ANSI/__init__.py
epitech_console/ANSI/ansi.py
epitech_console/ANSI/basepack.py
epitech_console/ANSI/color.py
epitech_console/ANSI/cursor.py
epitech_console/ANSI/line.py
epitech_console/Animation/__init__.py
epitech_console/Animation/animation.py
epitech_console/Animation/basepack.py
epitech_console/Animation/progressbar.py
epitech_console/Animation/spinner.py
epitech_console/Animation/style.py
epitech_console/Error/__init__.py
epitech_console/Error/error.py
epitech_console/System/__init__.py
epitech_console/System/action.py
epitech_console/System/config.py
epitech_console/System/console.py
epitech_console/System/log.py
epitech_console/System/setting.py
epitech_console/System/stopwatch.py
epitech_console/System/time.py
epitech_console/Text/__init__.py
epitech_console/Text/format.py
epitech_console/Text/text.py
epitech_console-0.1.8.3.dist-info/licenses/LICENSE
epitech_console-0.1.8.3.dist-info/METADATA
epitech_console-0.1.8.3.dist-info/WHEEL
epitech_console-0.1.8.3.dist-info/top_level.txt
epitech_console-0.1.8.3.dist-info/RECORD
