Metadata-Version: 2.4
Name: epitech_console
Version: 0.1.8.3
Summary: Console tools (animation / colored printing / formating / etc...)
Author-email: Nathan Jarjarbin <nathan.amaraggi@epitech.eu>
License-Expression: GPL-3.0-or-later
Project-URL: Homepage, https://jarjarbin06.github.io/epitech_console/
Project-URL: Repository, https://github.com/Jarjarbin06/epitech_console/v0.1.8
Project-URL: Issues, https://github.com/Jarjarbin06/epitech_console/issues
Classifier: Programming Language :: Python :: 3.13
Classifier: Operating System :: OS Independent
Classifier: Environment :: Console
Classifier: Development Status :: 3 - Alpha
Classifier: Intended Audience :: Developers
Classifier: Topic :: Software Development :: Libraries
Classifier: Topic :: Terminals
Classifier: Topic :: Utilities
Requires-Python: >=3.11
License-File: LICENSE
Requires-Dist: datetime
Dynamic: license-file
